cadastro_orama/__init__.py
cadastro_orama/api_client.py
cadastro_orama/configuration.py
cadastro_orama/exceptions.py
cadastro_orama/rest.py
cadastro_orama/api/__init__.py
cadastro_orama/api/developers_api.py
cadastro_orama/api/users_api.py
cadastro_orama/models/__init__.py
cadastro_orama/models/aprovacao.py
cadastro_orama/models/autenticacao_codigo_objeto.py
cadastro_orama/models/autenticacao_objeto.py
cadastro_orama/models/confirmado.py
cadastro_orama/models/conta_bancaria.py
cadastro_orama/models/dados_patrimonial.py
cadastro_orama/models/dados_profissionais.py
cadastro_orama/models/documento.py
cadastro_orama/models/documento_corpo.py
cadastro_orama/models/endereco.py
cadastro_orama/models/erro.py
cadastro_orama/models/front_end_step.py
cadastro_orama/models/lista_perfil_usuario.py
cadastro_orama/models/login_criado.py
cadastro_orama/models/login_objeto.py
cadastro_orama/models/login_senha_objeto.py
cadastro_orama/models/perfil_usuario.py
cadastro_orama/models/submetido.py
cadastro_orama/models/usuario_senha_objeto.py
openapi_client/__init__.py
openapi_client/api_client.py
openapi_client/configuration.py
openapi_client/exceptions.py
openapi_client/rest.py
openapi_client/api/__init__.py
openapi_client/api/developers_api.py
openapi_client/api/users_api.py
openapi_client/models/__init__.py
openapi_client/models/aprovacao.py
openapi_client/models/autenticacao_codigo_objeto.py
openapi_client/models/autenticacao_objeto.py
openapi_client/models/confirmado.py
openapi_client/models/conta_bancaria.py
openapi_client/models/dados_patrimonial.py
openapi_client/models/dados_profissionais.py
openapi_client/models/documento.py
openapi_client/models/documento_corpo.py
openapi_client/models/endereco.py
openapi_client/models/erro.py
openapi_client/models/lista_perfil_usuario.py
openapi_client/models/login_criado.py
openapi_client/models/login_objeto.py
openapi_client/models/login_senha_objeto.py
openapi_client/models/perfil_usuario.py
openapi_client/models/submetido.py
cadastro_orama-1.0.3.dist-info/METADATA
cadastro_orama-1.0.3.dist-info/WHEEL
cadastro_orama-1.0.3.dist-info/top_level.txt
cadastro_orama-1.0.3.dist-info/RECORD
