Metadata-Version: 2.1
Name: cadastro-orama
Version: 1.0.3
Summary: Criação de Contas
Home-page: UNKNOWN
Author: OpenAPI Generator community
Author-email: cadastro_api@orama.com.br
License: Apache 2.0
Keywords: OpenAPI,OpenAPI-Generator,Criação de Contas
Platform: UNKNOWN
Requires-Dist: urllib3 (>=1.15)
Requires-Dist: six (>=1.10)
Requires-Dist: certifi
Requires-Dist: python-dateutil
